k3time/__init__.py
k3time/tm.py
k3time-0.1.10.dist-info/licenses/LICENSE
k3time-0.1.10.dist-info/METADATA
k3time-0.1.10.dist-info/WHEEL
k3time-0.1.10.dist-info/top_level.txt
k3time-0.1.10.dist-info/RECORD
